setup.py
Huxley.egg-info/PKG-INFO
Huxley.egg-info/SOURCES.txt
Huxley.egg-info/dependency_links.txt
Huxley.egg-info/entry_points.txt
Huxley.egg-info/requires.txt
Huxley.egg-info/top_level.txt
huxley/__init__.py
huxley/cmdline.py
huxley/consts.py
huxley/errors.py
huxley/images.py
huxley/integration.py
huxley/main.py
huxley/run.py
huxley/steps.py
huxley/threadpool.py
huxley/version.py