Metadata-Version: 1.0
Name: Huxley
Version: 0.5
Summary: Watches you browse, takes screenshots, tells you when they change.
Home-page: http://github.com/facebook/huxley
Author: Pete Hunt
Author-email: pete.hunt@fb.com
License: Apache 2
Keywords: selenium testing facebook instagram
Platform: UNKNOWN
